MANIFEST.in
README.md
pyproject.toml
setup.py
./ttygif/cast2gif.c
./ttygif/version.c
./ttygif/asciicast/reader.c
./ttygif/gif/CommentExtension.c
./ttygif/gif/PlainTextExtension.c
./ttygif/gif/application_extension.c
./ttygif/gif/canvas.c
./ttygif/gif/color_table.c
./ttygif/gif/decode.c
./ttygif/gif/encode.c
./ttygif/gif/gif.c
./ttygif/gif/graphics_control_extension.c
./ttygif/gif/header.c
./ttygif/gif/image.c
./ttygif/gif/image_descriptor.c
./ttygif/gif/stream.c
./ttygif/gif/trailer.c
./ttygif/tools/passthrough.c
./ttygif/tty/display_state.c
./ttygif/tty/font.c
./ttygif/tty/graphics.c
./ttygif/tty/image.c
./ttygif/tty/parser.c
./ttygif/tty/terminal_emulator.c
./ttygif/tty/terminal_graphics.c
./ttygif/tty/theme.c
ttygif/__init__.py
ttygif/cli.py
ttygif/underlay.py
ttygif/version.py
ttygif.egg-info/PKG-INFO
ttygif.egg-info/SOURCES.txt
ttygif.egg-info/dependency_links.txt
ttygif.egg-info/entry_points.txt
ttygif.egg-info/requires.txt
ttygif.egg-info/top_level.txt
ttygif/asciicast/__init__.py
ttygif/asciicast/reader.py
ttygif/gif/CommentExtension.py
ttygif/gif/PlainTextExtension.py
ttygif/gif/__init__.py
ttygif/gif/application_extension.py
ttygif/gif/canvas.py
ttygif/gif/color_table.py
ttygif/gif/encode.py
ttygif/gif/gif.py
ttygif/gif/graphics_control_extension.py
ttygif/gif/header.py
ttygif/gif/image_descriptor.py
ttygif/gif/remap.py
ttygif/gif/trailer.py
ttygif/tools/__init__.py
ttygif/tools/bin2py.py
ttygif/tools/gen_charset.py
ttygif/tools/passthrough.py
ttygif/tty/__init__.py
ttygif/tty/fonts/AMI_BIOS.fd
ttygif/tty/fonts/ATI_8x14.fd
ttygif/tty/fonts/ATI_8x16.fd
ttygif/tty/fonts/ATI_8x8.fd
ttygif/tty/fonts/ATI_9x14.fd
ttygif/tty/fonts/ATI_9x16.fd
ttygif/tty/fonts/ATI_SmallW_6x8.fd
ttygif/tty/fonts/ATT_PC6300.fd
ttygif/tty/fonts/AmstradPC1512.fd
ttygif/tty/fonts/CompaqThin_8x14.fd
ttygif/tty/fonts/CompaqThin_8x16.fd
ttygif/tty/fonts/CompaqThin_8x8.fd
ttygif/tty/fonts/DTK_BIOS.fd
ttygif/tty/fonts/IBM_3270pc.fd
ttygif/tty/fonts/IBM_BIOS.fd
ttygif/tty/fonts/IBM_CGA.fd
ttygif/tty/fonts/IBM_CGAthin.fd
ttygif/tty/fonts/IBM_Conv.fd
ttygif/tty/fonts/IBM_EGA8.fd
ttygif/tty/fonts/IBM_EGA9.fd
ttygif/tty/fonts/IBM_ISO8.fd
ttygif/tty/fonts/IBM_ISO9.fd
