Metadata-Version: 2.1
Name: ttygif
Version: 1.2.640
Summary: A asciicast to gif utility
Home-page: https://github.com/chris17453/ttygif/
Author: Chris Watkins
Author-email: chris@watkinslabs.com
License: Creative Commons Attribution-Noncommercial-Share Alike license
Platform: UNKNOWN
Classifier: Programming Language :: Python :: 2.7
Classifier: Programming Language :: Python :: 3.7
Classifier: Development Status :: 3 - Alpha
Classifier: Operating System :: OS Independent
